[{"word":"\u0e1b\u0e23\u0e30\u0e14\u0e31\u0e1a\u0e44\u0e1fLightUp","frequency":9},{"word":"CitizenPortalRoadmap","frequency":7},{"word":"\u0e04\u0e2d\u0e19\u0e40\u0e2a\u0e34\u0e23\u0e4c\u0e15\u0e07\u0e32\u0e19\u0e0a\u0e49\u0e32\u0e07\u0e41\u0e1f\u0e23\u0e4c","frequency":7},{"word":"\u0e15\u0e38\u0e25\u0e32\u0e01\u0e32\u0e23\u0e1e\u0e23\u0e30\u0e18\u0e23\u0e23\u0e21\u0e19\u0e39","frequency":6},{"word":"\u0e40\u0e23\u0e15\u0e15\u0e34\u0e49\u0e07\u0e23\u0e35\u0e23\u0e31\u0e19\u0e15\u0e2d\u0e19\u0e08\u0e1a","frequency":6},{"word":"FullMoonFullSale","frequency":5},{"word":"OldGlamSweetheart","frequency":5},{"word":"\u0e14\u0e39\u0e16\u0e39\u0e01\u0e40\u0e2b\u0e22\u0e35\u0e22\u0e14\u0e2b\u0e22\u0e32\u0e21\u0e2a\u0e1a\u0e1b\u0e23\u0e30\u0e21\u0e32\u0e17","frequency":5},{"word":"\u0e04\u0e2d\u0e19\u0e40\u0e2a\u0e34\u0e23\u0e4c\u0e15\u0e21\u0e2b\u0e31\u0e28\u0e08\u0e23\u0e23\u0e22\u0e4c\u0e07\u0e32\u0e19\u0e0a\u0e49\u0e32\u0e07","frequency":4},{"word":"CatchfakeBrandname","frequency":4},{"word":"\u0e40\u0e1b\u0e47\u0e19\u0e2b\u0e19\u0e35\u0e49\u0e04\u0e48\u0e32\u0e08\u0e49\u0e32\u0e07\u0e40\u0e14\u0e34\u0e19\u0e23\u0e16","frequency":4},{"word":"AutomatedPeopleMover","frequency":4},{"word":"\u0e23\u0e16\u0e40\u0e21\u0e25\u0e4c\u0e23\u0e16\u0e15\u0e39\u0e49\u0e23\u0e16\u0e2a\u0e2d\u0e07\u0e41\u0e16\u0e27\u0e23\u0e16\u0e41\u0e17\u0e47\u0e01\u0e0b\u0e35\u0e48","frequency":4},{"word":"dePeauBeaut","frequency":4},{"word":"GREENFORFUTURE","frequency":4},{"word":"\u0e1a\u0e21\u0e08.\u0e2d\u0e35\u0e2a\u0e40\u0e17\u0e34\u0e23\u0e4c\u0e19\u0e42\u0e1e\u0e25","frequency":4},{"word":"PropertyGuruAsiaPropertyAwards","frequency":4},{"word":"Lessismore","frequency":4},{"word":"MC20FuoriserieEdition","frequency":3},{"word":"BKKMobileVaccinationUnit","frequency":3},{"word":"\u0e1b\u0e23\u0e30\u0e08\u0e33\u0e08\u0e31\u0e07\u0e2b\u0e27\u0e31\u0e14\u0e2d\u0e38\u0e17\u0e31\u0e22\u0e18\u0e32\u0e19\u0e35\u0e40\u0e02\u0e15\u0e40\u0e25\u0e37\u0e2d\u0e01\u0e15\u0e31\u0e49\u0e07","frequency":3},{"word":"\u0e1b\u0e23\u0e30\u0e01\u0e27\u0e14MissUniverse","frequency":3},{"word":"\u0e19\u0e31\u0e01\u0e42\u0e17\u0e29\u0e04\u0e14\u0e35\u0e2d\u0e38\u0e01\u0e09\u0e01\u0e23\u0e23\u0e08\u0e4c\u0e2a\u0e30\u0e40\u0e17\u0e37\u0e2d\u0e19\u0e02\u0e27\u0e31\u0e0d","frequency":3},{"word":"Zincfingerantiviralprotein","frequency":3},{"word":"MostPowerfulBrands","frequency":3},{"word":"MUFGVirtualBusinessMatchingFair","frequency":3},{"word":"\u0e22\u0e36\u0e14\u0e17\u0e23\u0e31\u0e1e\u0e22\u0e4c\u0e2a\u0e34\u0e19\u0e43\u0e0a\u0e49\u0e04\u0e48\u0e32\u0e1b\u0e23\u0e31\u0e1a","frequency":3},{"word":"\u0e19\u0e49\u0e2d\u0e21\u0e23\u0e31\u0e1a\u0e04\u0e33\u0e15\u0e34\u0e0a\u0e21","frequency":3},{"word":"\u0e0b\u0e38\u0e1b\u0e40\u0e1b\u0e2d\u0e23\u0e4c\u0e04\u0e32\u0e23\u0e4cMC20","frequency":2},{"word":"wishbonewithvirtualsteeringaxle","frequency":2},{"word":"\u0e2d\u0e2d\u0e19\u0e41\u0e2d\u0e23\u0e4c\u0e2d\u0e2d\u0e19\u0e01\u0e23\u0e32\u0e27","frequency":2},{"word":"\u0e2d\u0e2d\u0e19\u0e40\u0e1b\u0e40\u0e1b\u0e2d\u0e23\u0e4c\u0e2d\u0e2d\u0e19","frequency":2},{"word":"\u0e2d\u0e32\u0e01\u0e32\u0e23\u0e2a\u0e32\u0e2b\u0e31\u0e2a\u0e2b\u0e21\u0e14\u0e2a\u0e15\u0e34\u0e44\u0e21\u0e48\u0e23\u0e39\u0e49\u0e2a\u0e36\u0e01\u0e15\u0e31\u0e27","frequency":2},{"word":"\u0e2b\u0e37\u0e48\u0e19\u0e01\u0e32\u0e21\u0e02\u0e22\u0e30\u0e2a\u0e31\u0e07\u0e04\u0e21","frequency":2},{"word":"DIPROMMOTOROUTLET","frequency":2},{"word":"FlexSelectedPartySet","frequency":2},{"word":"\u0e25\u0e32\u0e14\u0e15\u0e23\u0e30\u0e40\u0e27\u0e19\u0e2b\u0e19\u0e48\u0e27\u0e22\u0e40\u0e09\u0e1e\u0e32\u0e30\u0e01\u0e34\u0e08\u0e01\u0e23\u0e21\u0e17\u0e2b\u0e32\u0e23\u0e23\u0e32\u0e1a","frequency":2},{"word":"MobileStrokeUnit","frequency":2},{"word":"StrokeOneStop","frequency":2},{"word":"\u0e28\u0e34\u0e23\u0e34\u0e23\u0e32\u0e0a\u0e04\u0e13\u0e30\u0e27\u0e34\u0e28\u0e27\u0e01\u0e23\u0e23\u0e21\u0e28\u0e32\u0e2a\u0e15\u0e23\u0e4c\u0e21\u0e2b\u0e32\u0e27\u0e34\u0e17\u0e22\u0e32\u0e25\u0e31\u0e22\u0e21\u0e2b\u0e34\u0e14\u0e25","frequency":2},{"word":"\u0e09\u0e35\u0e14\u0e22\u0e32\u0e2a\u0e25\u0e32\u0e22\u0e25\u0e34\u0e48\u0e21","frequency":2},{"word":"catchfakebrandname","frequency":2},{"word":"\u0e14\u0e27\u0e07\u0e14\u0e32\u0e27BOYSOVERFLOWERS","frequency":2},{"word":"\u0e0b\u0e36\u0e21\u0e42\u0e2d\u0e49\u0e22\u0e40\u0e19\u0e2d\u0e30","frequency":2},{"word":"JaapvanDissel","frequency":2},{"word":"\u0e21\u0e32\u0e19\u0e30\u0e01\u0e25\u0e35\u0e1a\u0e2a\u0e31\u0e15","frequency":2},{"word":"\u0e40\u0e04\u0e23\u0e37\u0e48\u0e2d\u0e07\u0e43\u0e0a\u0e49\u0e44\u0e1f\u0e1f\u0e49\u0e32\u0e2b\u0e25\u0e2d\u0e14\u0e44\u0e1f\u0e1f\u0e49\u0e32\u0e2b\u0e25\u0e2d\u0e14\u0e44\u0e1f\u0e42\u0e0b\u0e25","frequency":2},{"word":"\u0e01\u0e23\u0e30\u0e40\u0e1b\u0e4b\u0e32\u0e40\u0e14\u0e34\u0e19\u0e17\u0e32\u0e07\u0e1b\u0e25\u0e32\u0e23\u0e49\u0e32\u0e1a\u0e49\u0e32\u0e19\u0e44\u0e23\u0e48","frequency":2},{"word":"\u0e2d\u0e19\u0e38\u0e2a\u0e32\u0e27\u0e23\u0e35\u0e22\u0e4c\u0e17\u0e49\u0e32\u0e27\u0e2a\u0e38\u0e23\u0e19\u0e32\u0e23\u0e35","frequency":2},{"word":"\u0e08\u0e39\u0e07\u0e0d\u0e32\u0e15\u0e34\u0e1c\u0e39\u0e49\u0e43\u0e2b\u0e0d\u0e48\u0e04\u0e38\u0e13\u0e15\u0e32\u0e04\u0e38\u0e13\u0e22\u0e32\u0e22","frequency":2},{"word":"\u0e21\u0e2d\u0e0d\u0e23\u0e32\u0e21\u0e31\u0e0d\u0e23\u0e34\u0e21\u0e1d\u0e31\u0e48\u0e07","frequency":2},{"word":"SimpleRandomSampling","frequency":2},{"word":"\u0e42\u0e04\u0e23\u0e07\u0e01\u0e32\u0e23\u0e19\u0e33\u0e23\u0e48\u0e2d\u0e07OneID","frequency":2},{"word":"SingleSignOne","frequency":2},{"word":"\u0e2b\u0e31\u0e27\u0e40\u0e09\u0e35\u0e22\u0e27\u0e40\u0e09\u0e25\u0e34\u0e21\u0e1e\u0e23\u0e30\u0e40\u0e01\u0e35\u0e22\u0e23\u0e15\u0e34\u0e15\u0e34\u0e14\u0e15\u0e48\u0e2d\u0e2a\u0e2d\u0e1a\u0e16\u0e32\u0e21","frequency":2},{"word":"Kmoverall","frequency":2},{"word":"Evusheld\u0e21\u0e35\u0e23\u0e30\u0e14\u0e31\u0e1aInhibitoryConcentration","frequency":2},{"word":"CorePCEPriceIndices","frequency":2},{"word":"SET50SET100sSETSETCLMVSETHDSETTHSI","frequency":2},{"word":"\u0e1a\u0e21\u0e08.\u0e2a\u0e01\u0e32\u0e22\u0e44\u0e2d\u0e0b\u0e35","frequency":2},{"word":"\u0e1a\u0e21\u0e08.\u0e27\u0e32\u0e27\u0e41\u0e1f\u0e04\u0e40\u0e15\u0e2d\u0e23\u0e4c","frequency":2},{"word":"\u0e01\u0e49\u0e19\u0e01\u0e23\u0e30\u0e1b\u0e4b\u0e2d\u0e07\u0e41\u0e1a\u0e19\u0e40\u0e23\u0e35\u0e22\u0e1a","frequency":2},{"word":"\u0e04\u0e25\u0e37\u0e48\u0e19\u0e44\u0e2a\u0e49\u0e2d\u0e32\u0e40\u0e08\u0e35\u0e22\u0e19\u0e01\u0e25\u0e49\u0e32\u0e21\u0e40\u0e19\u0e37\u0e49\u0e2d","frequency":2},{"word":"\u0e1e\u0e23\u0e48\u0e32\u0e21\u0e31\u0e27\u0e0b\u0e36\u0e21\u0e07\u0e48\u0e27\u0e07\u0e01\u0e25\u0e37\u0e19","frequency":2},{"word":"\u0e01\u0e25\u0e49\u0e32\u0e21\u0e40\u0e19\u0e37\u0e49\u0e2d\u0e15\u0e49\u0e19\u0e04\u0e2d\u0e2d\u0e48\u0e2d\u0e19\u0e41\u0e23\u0e07","frequency":2},{"word":"THESTRANDTHONGLOR","frequency":2},{"word":"THESTRANDPark","frequency":2},{"word":"PrivateJetTerminal","frequency":2},{"word":"\u0e40\u0e28\u0e23\u0e29\u0e10\u0e35\u0e1b\u0e23\u0e30\u0e04\u0e2d\u0e07\u0e40\u0e27\u0e0a","frequency":2},{"word":"\u0e40\u0e2d\u0e01\u0e20\u0e32\u0e1e\u0e40\u0e1b\u0e47\u0e19\u0e1b\u0e36\u0e01\u0e41\u0e1c\u0e48\u0e19\u0e08\u0e07\u0e23\u0e31\u0e01\u0e20\u0e31\u0e01\u0e14\u0e35\u0e0b\u0e37\u0e48\u0e2d\u0e2a\u0e31\u0e15\u0e22\u0e4c\u0e2a\u0e38\u0e08\u0e23\u0e34\u0e15","frequency":2},{"word":"hai","frequency":2},{"word":"\u0e1b\u0e39\u0e48\u0e25\u0e30\u0e40\u0e25\u0e34\u0e07\u0e2b\u0e27\u0e32\u0e22","frequency":2},{"word":"\u0e40\u0e2a\u0e35\u0e22\u0e2b\u0e25\u0e31\u0e01\u0e1e\u0e38\u0e48\u0e07\u0e0a\u0e19\u0e17\u0e32\u0e07\u0e40\u0e1a\u0e35\u0e48\u0e22\u0e07","frequency":2},{"word":"\u0e23\u0e16\u0e1e\u0e48\u0e27\u0e07\u0e1e\u0e38\u0e48\u0e07\u0e0a\u0e19\u0e15\u0e34\u0e14\u0e01\u0e31\u0e1a","frequency":2},{"word":"\u0e16\u0e49\u0e27\u0e19\u0e2b\u0e19\u0e49\u0e32\u0e40\u0e17\u0e48\u0e32\u0e40\u0e17\u0e35\u0e22\u0e21\u0e01\u0e31\u0e19","frequency":2},{"word":"\u0e40\u0e1a\u0e35\u0e49\u0e22\u0e2b\u0e27\u0e31\u0e14\u0e1a\u0e33\u0e40\u0e2b\u0e19\u0e47\u0e08\u0e1a\u0e33\u0e19\u0e32\u0e0d","frequency":2},{"word":"mainusecase","frequency":2},{"word":"BestLandscapeArchitecturalDesign","frequency":2},{"word":"DigitalHealthPass","frequency":2},{"word":"\u0e17\u0e34\u0e28\u0e15\u0e30\u0e27\u0e31\u0e19\u0e15\u0e01\u0e04\u0e48\u0e2d\u0e19\u0e17\u0e32\u0e07\u0e40\u0e2b\u0e19\u0e37\u0e2d","frequency":2},{"word":"\u0e2b\u0e25\u0e31\u0e48\u0e07\u0e19\u0e49\u0e33\u0e15\u0e32\u0e44\u0e2b\u0e25\u0e2d\u0e32\u0e1a","frequency":2},{"word":"\u0e14\u0e35\u0e01\u0e23\u0e35\u0e40\u0e2b\u0e23\u0e35\u0e22\u0e0d\u0e17\u0e2d\u0e07\u0e41\u0e14\u0e07\u0e0b\u0e35\u0e40\u0e01\u0e21\u0e2a\u0e4c","frequency":2},{"word":"HSBCBWFWORLDTOURFINALS","frequency":2}]