[{"word":"CentralBlackMidnightSale","frequency":11},{"word":"PortoWorldwideLimited","frequency":9},{"word":"AgriBIZIdolDevelopmentProject","frequency":9},{"word":"ThreeManDown","frequency":8},{"word":"5GTHAILANDBIGMOVE","frequency":8},{"word":"ClubFridayShow","frequency":7},{"word":"\u0e01\u0e25\u0e49\u0e2d\u0e07\u0e42\u0e17\u0e23\u0e17\u0e23\u0e23\u0e28\u0e19\u0e4c\u0e2d\u0e27\u0e01\u0e32\u0e28\u0e40\u0e08\u0e21\u0e2a\u0e4c","frequency":7},{"word":"\u0e1a\u0e48\u0e2d\u0e19\u0e01\u0e32\u0e2a\u0e34\u0e42\u0e19\u0e16\u0e39\u0e01\u0e01\u0e0e\u0e2b\u0e21\u0e32\u0e22","frequency":6},{"word":"DigitalGovernmentAwards","frequency":6},{"word":"AFFSUZUKICUP","frequency":6},{"word":"RobinhoodEVBike","frequency":6},{"word":"HomeProSuperExpo","frequency":5},{"word":"GrabHoldingsLimited","frequency":5},{"word":"\u0e15\u0e25\u0e32\u0e14\u0e2b\u0e25\u0e31\u0e01\u0e17\u0e23\u0e31\u0e1e\u0e22\u0e4cNASDAQ\u0e1b\u0e23\u0e30\u0e40\u0e17\u0e28\u0e2a\u0e2b\u0e23\u0e31\u0e10\u0e2d\u0e40\u0e21\u0e23\u0e34\u0e01\u0e32","frequency":5},{"word":"\u0e40\u0e0b\u0e47\u0e19\u0e40\u0e0b\u0e2d\u0e23\u0e4c\u0e44\u0e23\u0e49\u0e2a\u0e32\u0e22OsseosurfaceElectronics","frequency":5},{"word":"SuperBrandSuperDeal","frequency":4},{"word":"\u0e22\u0e35\u0e19\u0e2b\u0e19\u0e32\u0e21\u0e41\u0e2b\u0e25\u0e21","frequency":4},{"word":"\u0e2a\u0e32\u0e23\u0e04\u0e14\u0e35\u0e19\u0e49\u0e2d\u0e21\u0e23\u0e33\u0e25\u0e36\u0e01","frequency":4},{"word":"\u0e2d\u0e34\u0e2a\u0e23\u0e32\u0e40\u0e2d\u0e25\u0e2d\u0e2d\u0e2a\u0e40\u0e15\u0e23\u0e35\u0e22\u0e40\u0e01\u0e32\u0e2b\u0e25\u0e35\u0e43\u0e15\u0e49","frequency":4},{"word":"ThaiPBSSci","frequency":4},{"word":"Tech","frequency":4},{"word":"AFFSuzukiCup","frequency":4},{"word":"PTMaxCard","frequency":4},{"word":"LAMYSurpriseBox","frequency":4},{"word":"HeartByHeart","frequency":4},{"word":"\u0e04\u0e49\u0e2d\u0e19\u0e15\u0e2d\u0e01\u0e15\u0e30\u0e1b\u0e39","frequency":4},{"word":"MINICOOPERSE","frequency":3},{"word":"\u0e1a\u0e17\u0e40\u0e1e\u0e25\u0e07\u0e1e\u0e23\u0e30\u0e23\u0e32\u0e0a\u0e19\u0e34\u0e1e\u0e19\u0e18\u0e4c\u0e40\u0e1e\u0e25\u0e07\u0e44\u0e17\u0e22\u0e40\u0e14\u0e34\u0e21","frequency":3},{"word":"\u0e42\u0e15\u0e4a\u0e30\u0e2b\u0e21\u0e39\u0e48\u0e1b\u0e23\u0e30\u0e14\u0e34\u0e29\u0e10\u0e32\u0e19\u0e1e\u0e23\u0e30\u0e1a\u0e23\u0e21\u0e09\u0e32\u0e22\u0e32\u0e25\u0e31\u0e01\u0e29\u0e13\u0e4c","frequency":3},{"word":"\u0e44\u0e1e\u0e28\u0e32\u0e25\u0e0a\u0e48\u0e2d\u0e1c\u0e01\u0e32","frequency":3},{"word":"\u0e21\u0e32\u0e19\u0e30\u0e01\u0e25\u0e35\u0e1a\u0e2a\u0e31\u0e15","frequency":3},{"word":"SellersGrowBeyond","frequency":3},{"word":"LADYPINKSHOP","frequency":3},{"word":"\u0e41\u0e2b\u0e25\u0e48\u0e07\u0e1c\u0e25\u0e34\u0e15\u0e19\u0e49\u0e33\u0e1b\u0e23\u0e30\u0e1b\u0e32\u0e14\u0e34\u0e1a","frequency":3},{"word":"\u0e1a\u0e48\u0e27\u0e07\u0e41\u0e23\u0e49\u0e27\u0e23\u0e31\u0e14\u0e02\u0e49\u0e2d\u0e40\u0e17\u0e49\u0e32","frequency":3},{"word":"\u0e40\u0e2d\u0e47\u0e19\u0e40\u0e15\u0e2d\u0e23\u0e4c\u0e40\u0e17\u0e19\u0e40\u0e21\u0e49\u0e19\u0e17\u0e4c\u0e04\u0e2d\u0e21\u0e40\u0e1e\u0e25\u0e47\u0e01\u0e0b\u0e4c","frequency":3},{"word":"DRIVENEWECONOMY","frequency":3},{"word":"CentralDepartmentStore","frequency":3},{"word":"\u0e40\u0e27\u0e0a\u0e28\u0e32\u0e2a\u0e15\u0e23\u0e4c\u0e40\u0e02\u0e15\u0e23\u0e49\u0e2d\u0e19\u0e21\u0e2b\u0e32\u0e27\u0e34\u0e17\u0e22\u0e32\u0e25\u0e31\u0e22\u0e21\u0e2b\u0e34\u0e14\u0e25","frequency":3},{"word":"\u0e40\u0e01\u0e23\u0e14\u0e15\u0e31\u0e27\u0e40\u0e01\u0e47\u0e1a\u0e1b\u0e23\u0e30\u0e08\u0e38\u0e22\u0e34\u0e48\u0e07\u0e22\u0e27\u0e14","frequency":3},{"word":"\u0e40\u0e1b\u0e25\u0e37\u0e2d\u0e01\u0e25\u0e33\u0e15\u0e49\u0e19\u0e01\u0e34\u0e48\u0e07\u0e01\u0e49\u0e32\u0e19","frequency":3},{"word":"SchoolasLearningCommunity","frequency":3},{"word":"FujitsuDigitalAnnealer","frequency":3},{"word":"\u0e23\u0e16\u0e1a\u0e31\u0e2a\u0e42\u0e14\u0e22\u0e2a\u0e32\u0e23VIPBUS","frequency":3},{"word":"onestopservice","frequency":3},{"word":"\u0e27\u0e34\u0e11\u0e39\u0e23\u0e22\u0e4c\u0e2b\u0e31\u0e2a\u0e20\u0e32\u0e04\u0e22\u0e4c","frequency":3},{"word":"\u0e42\u0e2e\u0e21\u0e42\u0e1b\u0e23\u0e14\u0e31\u0e01\u0e2a\u0e4c\u0e40\u0e0b\u0e47\u0e19\u0e40\u0e15\u0e2d\u0e23\u0e4c","frequency":2},{"word":"\u0e1a\u0e31\u0e15\u0e23\u0e40\u0e04\u0e23\u0e14\u0e34\u0e15\u0e42\u0e2e\u0e21\u0e42\u0e1b\u0e23\u0e27\u0e35\u0e0b\u0e48\u0e32\u0e41\u0e1e\u0e25\u0e17\u0e34\u0e19\u0e31\u0e21","frequency":2},{"word":"SuperGiftVoucher","frequency":2},{"word":"HomeProSUPEREXPO","frequency":2},{"word":"ORANGETHEWORLD","frequency":2},{"word":"29thAnniversarypresents","frequency":2},{"word":"BABYFACECLUBTHAILAND","frequency":2},{"word":"sacitofficial","frequency":2},{"word":"\u0e1e\u0e32\u0e23\u0e4c\u0e04\u0e1e\u0e32\u0e23\u0e32\u0e01\u0e2d\u0e19\u0e23\u0e34\u0e40\u0e27\u0e2d\u0e23\u0e4c\u0e1e\u0e32\u0e23\u0e4c\u0e04","frequency":2},{"word":"\u0e04\u0e39\u0e48\u0e2a\u0e21\u0e23\u0e2a\u0e04\u0e13\u0e30\u0e23\u0e31\u0e10\u0e21\u0e19\u0e15\u0e23\u0e35\u0e2a\u0e48\u0e27\u0e19\u0e20\u0e39\u0e21\u0e34\u0e20\u0e32\u0e04","frequency":2},{"word":"\u0e04\u0e33\u0e01\u0e25\u0e48\u0e32\u0e27\u0e19\u0e49\u0e2d\u0e21\u0e23\u0e33\u0e25\u0e36\u0e01","frequency":2},{"word":"\u0e1e\u0e22\u0e31\u0e04\u0e06\u0e4c\u0e2d\u0e23\u0e38\u0e13\u0e19\u0e31\u0e01\u0e21\u0e27\u0e22","frequency":2},{"word":"\u0e2a\u0e01\u0e4a\u0e2d\u0e15\u0e40\u0e1e\u0e35\u0e22\u0e27\u0e40\u0e23\u0e48","frequency":2},{"word":"\u0e21\u0e34\u0e19\u0e48\u0e32\u0e2b\u0e25\u0e31\u0e07\u0e46\u0e42\u0e2d\u0e21","frequency":2},{"word":"\u0e2a\u0e16\u0e32\u0e19\u0e1a\u0e31\u0e19\u0e40\u0e17\u0e34\u0e07\u0e1c\u0e31\u0e1a\u0e04\u0e25\u0e31\u0e1a","frequency":2},{"word":"ThreeManDown6","frequency":2},{"word":"Apple\u0e1c\u0e39\u0e49\u0e08\u0e33\u0e2b\u0e19\u0e48\u0e32\u0e22\u0e2a\u0e21\u0e32\u0e23\u0e4c\u0e17\u0e42\u0e1f\u0e19","frequency":2},{"word":"\u0e2a\u0e21\u0e32\u0e23\u0e4c\u0e17\u0e42\u0e1f\u0e19\u0e23\u0e38\u0e48\u0e19\u0e43\u0e2b\u0e21\u0e48\u0e46","frequency":2},{"word":"3DFoodPrinter","frequency":2},{"word":"MicroFullMoon","frequency":2},{"word":"\u0e14\u0e32\u0e27\u0e2d\u0e31\u0e07\u0e04\u0e32\u0e23\u0e40\u0e04\u0e35\u0e22\u0e07\u0e14\u0e27\u0e07\u0e08\u0e31\u0e19\u0e17\u0e23\u0e4c","frequency":2},{"word":"\u0e14\u0e32\u0e27\u0e1e\u0e24\u0e2b\u0e31\u0e2a\u0e1a\u0e14\u0e35\u0e40\u0e04\u0e35\u0e22\u0e07\u0e14\u0e27\u0e07\u0e08\u0e31\u0e19\u0e17\u0e23\u0e4c","frequency":2},{"word":"\u0e14\u0e32\u0e27\u0e1e\u0e38\u0e18\u0e40\u0e04\u0e35\u0e22\u0e07\u0e14\u0e32\u0e27\u0e28\u0e38\u0e01\u0e23\u0e4c","frequency":2},{"word":"\u0e40\u0e17\u0e37\u0e2d\u0e01\u0e40\u0e02\u0e32\u0e1a\u0e23\u0e23\u0e17\u0e31\u0e14\u0e17\u0e30\u0e25\u0e31\u0e01","frequency":2},{"word":"\u0e17\u0e32\u0e22\u0e32\u0e06\u0e48\u0e32\u0e40\u0e0a\u0e37\u0e49\u0e2d\u0e40\u0e09\u0e1e\u0e32\u0e30\u0e17\u0e35\u0e48","frequency":2},{"word":"\u0e04\u0e27\u0e32\u0e21\u0e15\u0e01\u0e25\u0e07CPTPP\u0e2d\u0e22\u0e48\u0e32\u0e07\u0e16\u0e32\u0e27\u0e23\u0e43\u0e19\u0e17\u0e31\u0e19\u0e17\u0e35","frequency":2},{"word":"ValentinaSampaio\u0e19\u0e32\u0e07\u0e41\u0e1a\u0e1a","frequency":2},{"word":"OneNightStand","frequency":2},{"word":"THEFRENCHRESISTANCE","frequency":2},{"word":"\u0e19\u0e49\u0e2d\u0e21\u0e23\u0e33\u0e25\u0e36\u0e01\u0e16\u0e36\u0e07\u0e1e\u0e23\u0e30\u0e21\u0e2b\u0e32\u0e01\u0e23\u0e38\u0e13\u0e32\u0e18\u0e34\u0e04\u0e38\u0e13","frequency":2},{"word":"OneStopService","frequency":2},{"word":"DCFastCharger","frequency":2},{"word":"AutonomousEVCar","frequency":2},{"word":"\u0e2a\u0e37\u0e1a\u0e44\u0e1b","frequency":2},{"word":"\u0e40\u0e17\u0e34\u0e14\u0e1e\u0e23\u0e30\u0e40\u0e01\u0e35\u0e22\u0e23\u0e15\u0e34\u0e43\u0e19\u0e2b\u0e25\u0e27\u0e07\u0e23\u0e31\u0e0a\u0e01\u0e32\u0e25","frequency":2},{"word":"EcoIndustrialEstate","frequency":2},{"word":"RobinhoodEVPowerStation","frequency":2},{"word":"\u0e1a\u0e33\u0e1a\u0e31\u0e14OperationBIM","frequency":2},{"word":"SiamGiftCard","frequency":2},{"word":"ChainDrugStore","frequency":2},{"word":"\u0e23\u0e16\u0e1a\u0e31\u0e2a\u0e42\u0e14\u0e22\u0e2a\u0e32\u0e23\u0e27\u0e35\u0e44\u0e2d\u0e1e\u0e35","frequency":2},{"word":"\u0e19\u0e49\u0e33\u0e22\u0e32\u0e06\u0e48\u0e32\u0e40\u0e0a\u0e37\u0e49\u0e2d","frequency":2},{"word":"PainPoint\u0e04\u0e27\u0e32\u0e21\u0e23\u0e39\u0e49\u0e2a\u0e36\u0e01\u0e1c\u0e34\u0e14","frequency":2},{"word":"\u0e2b\u0e21\u0e2d\u0e19\u0e1c\u0e49\u0e32\u0e2b\u0e48\u0e21CentralBlackMidnightSale","frequency":2},{"word":"CENTRALDEPARTMENTSTORE","frequency":2},{"word":"CentralPersonalShopperOnDemand","frequency":2},{"word":"\u0e01\u0e49\u0e32\u0e19\u0e2a\u0e49\u0e21\u0e14\u0e48\u0e32\u0e07","frequency":2},{"word":"OxfordTropicalMedicineResearchUnit","frequency":2},{"word":"AdaptivePlatformClinicalTrial","frequency":2},{"word":"AgriBIZIdol","frequency":2},{"word":"\u0e40\u0e2a\u0e35\u0e22\u0e2b\u0e25\u0e31\u0e01\u0e1e\u0e25\u0e34\u0e01\u0e04\u0e27\u0e48\u0e33\u0e44\u0e16\u0e25","frequency":2},{"word":"\u0e42\u0e0a\u0e40\u0e1f\u0e2d\u0e23\u0e4c\u0e41\u0e17\u0e47\u0e01\u0e0b\u0e35\u0e48\u0e1b\u0e32\u0e14","frequency":2},{"word":"BRESingaporePte","frequency":2},{"word":"HaTinhSolarPowerJointStockCompany","frequency":2},{"word":"\u0e40\u0e21\u0e01\u0e30\u0e27\u0e31\u0e15\u0e15\u0e4c\u0e40\u0e17\u0e35\u0e22\u0e1a\u0e40\u0e17\u0e48\u0e32","frequency":2},{"word":"SolarPVECOSystem","frequency":2},{"word":"\u0e42\u0e14\u0e14\u0e2a\u0e23\u0e30\u0e19\u0e49\u0e33\u0e41\u0e01\u0e49\u0e1a\u0e19","frequency":2},{"word":"\u0e40\u0e15\u0e34\u0e21\u0e19\u0e49\u0e33\u0e21\u0e31\u0e19\u0e2d\u0e2d\u0e2a\u0e0b\u0e35\u0e48\u0e2d\u0e2d\u0e22\u0e25\u0e4c","frequency":2},{"word":"\u0e40\u0e04\u0e23\u0e1b\u0e44\u0e2a\u0e49\u0e1e\u0e39\u0e19","frequency":2},{"word":"\u0e01\u0e33\u0e08\u0e31\u0e14\u0e1b\u0e25\u0e27\u0e01Mr","frequency":2},{"word":"PRODUCTOFTHEYEARSAWARD","frequency":2},{"word":"\u0e04\u0e27\u0e32\u0e21\u0e08\u0e33\u0e40\u0e1e\u0e32\u0e30\u0e15\u0e48\u0e2d\u0e15\u0e31\u0e27","frequency":2},{"word":"\u0e0b\u0e2d\u0e1f\u0e15\u0e4c\u0e41\u0e27\u0e23\u0e4cSalesforceCRMSolution","frequency":2},{"word":"SUPERCRITICALFLUIDCO2EXTRACTION","frequency":2},{"word":"\u0e15\u0e33\u0e23\u0e31\u0e1a\u0e40\u0e21\u0e15\u0e15\u0e32\u0e42\u0e2d\u0e2a\u0e16","frequency":2},{"word":"\u0e15\u0e33\u0e23\u0e31\u0e1a\u0e01\u0e32\u0e23\u0e38\u0e13\u0e22\u0e4c\u0e42\u0e2d\u0e2a\u0e16","frequency":2},{"word":"\u0e40\u0e21\u0e40\u0e08\u0e2d\u0e23\u0e4c\u0e0b\u0e35\u0e19\u0e35\u0e40\u0e1e\u0e25\u0e47\u0e01\u0e0b\u0e4c\u0e01\u0e23\u0e38","frequency":2},{"word":"FeedInnovationWeek","frequency":2},{"word":"QuantumTechnologyFoundation","frequency":2},{"word":"PrincipalTargetDateRetirementFund","frequency":2},{"word":"\u0e17\u0e32\u0e07\u0e27\u0e34\u0e0a\u0e32\u0e01\u0e32\u0e23GTRAWorkshop","frequency":2},{"word":"\u0e01\u0e32\u0e23\u0e25\u0e07\u0e19\u0e32\u0e21\u0e15\u0e48\u0e2d\u0e2d\u0e32\u0e22\u0e38\u0e04\u0e27\u0e32\u0e21\u0e15\u0e01\u0e25\u0e07","frequency":2},{"word":"\u0e04\u0e13\u0e1a\u0e14\u0e35\u0e04\u0e13\u0e30\u0e27\u0e34\u0e28\u0e27\u0e01\u0e23\u0e23\u0e21\u0e28\u0e32\u0e2a\u0e15\u0e23\u0e4c\u0e21\u0e2b\u0e32\u0e27\u0e34\u0e17\u0e22\u0e32\u0e25\u0e31\u0e22\u0e21\u0e2b\u0e34\u0e14\u0e25","frequency":2},{"word":"ThaiRailwayAssociation","frequency":2},{"word":"SekManMak","frequency":2},{"word":"\u0e2b\u0e08\u0e01.\u0e40\u0e1b\u0e48\u0e32\u0e40\u0e1b\u0e32","frequency":2},{"word":"\u0e07\u0e32\u0e19\u0e01\u0e48\u0e2d\u0e2a\u0e23\u0e49\u0e32\u0e07\u0e2a\u0e19\u0e32\u0e21\u0e01\u0e35\u0e2c\u0e32\u0e21\u0e23\u0e20.","frequency":2},{"word":"\u0e0b\u0e31\u0e07\u0e2e\u0e35\u0e49\u0e17\u0e34\u0e28\u0e43\u0e15\u0e49","frequency":2},{"word":"\u0e2d\u0e19\u0e38\u0e2a\u0e32\u0e27\u0e23\u0e35\u0e22\u0e4c\u0e0a\u0e31\u0e22\u0e2a\u0e21\u0e23\u0e20\u0e39\u0e21\u0e34\u0e2a\u0e19\u0e32\u0e21\u0e28\u0e38\u0e20\u0e0a\u0e25\u0e32\u0e28\u0e31\u0e22\u0e27\u0e07\u0e40\u0e27\u0e35\u0e22\u0e19","frequency":2},{"word":"\u0e0a\u0e38\u0e14\u0e0a\u0e31\u0e49\u0e19\u0e43\u0e19\u0e41\u0e19\u0e17\u0e02\u0e31\u0e49\u0e19\u0e15\u0e48\u0e33","frequency":2},{"word":"\u0e1c\u0e31\u0e14\u0e40\u0e1c\u0e47\u0e14\u0e41\u0e21\u0e07\u0e21\u0e38\u0e21","frequency":2},{"word":"\u0e42\u0e04\u0e15\u0e23\u0e40\u0e1e\u0e0a\u0e0c\u0e06\u0e32\u0e15\u0e41\u0e04\u0e49\u0e19","frequency":2},{"word":"\u0e04\u0e27\u0e32\u0e21\u0e15\u0e37\u0e48\u0e19\u0e15\u0e31\u0e27\u0e01\u0e23\u0e30\u0e1b\u0e23\u0e35\u0e49\u0e01\u0e23\u0e30\u0e40\u0e1b\u0e23\u0e48\u0e32\u0e2a\u0e14\u0e0a\u0e37\u0e48\u0e19\u0e17\u0e31\u0e19\u0e17\u0e35\u0e17\u0e35\u0e48","frequency":2},{"word":"Musthaveitem","frequency":2},{"word":"\u0e1b\u0e23\u0e30\u0e01\u0e31\u0e19\u0e20\u0e31\u0e22\u0e42\u0e23\u0e04\u0e21\u0e30\u0e40\u0e23\u0e47\u0e07Cancer","frequency":2},{"word":"\u0e40\u0e15\u0e49\u0e32\u0e17\u0e36\u0e07\u0e40\u0e22\u0e32\u0e27\u0e23\u0e32\u0e0a\u0e40\u0e09\u0e32\u0e01\u0e4a\u0e27\u0e22","frequency":2},{"word":"\u0e40\u0e21\u0e35\u0e48\u0e22\u0e07\u0e01\u0e25\u0e35\u0e1a\u0e1a\u0e31\u0e27\u0e1a\u0e49\u0e32\u0e19\u0e2a\u0e27\u0e19","frequency":2},{"word":"\u0e1a\u0e49\u0e32\u0e1a\u0e34\u0e48\u0e19\u0e21\u0e30\u0e1e\u0e23\u0e49\u0e32\u0e27\u0e19\u0e49\u0e33\u0e2b\u0e2d\u0e21","frequency":2},{"word":"VarunaDronePilotTraining","frequency":2},{"word":"\u0e15\u0e2d\u0e01\u0e22\u0e33\u0e04\u0e27\u0e32\u0e21\u0e40\u0e1b\u0e47\u0e19\u0e1c\u0e39\u0e49\u0e19\u0e33","frequency":2},{"word":"PersonalAssistantRobot","frequency":2},{"word":"RDFPowerPlant","frequency":2},{"word":"RefuseDerivedFuel","frequency":2},{"word":"MediaMarketingInitiative","frequency":2},{"word":"CIMBTHAIDigitalBanking","frequency":2},{"word":"workfromhome","frequency":2},{"word":"HalfToastOfficial","frequency":2},{"word":"\u0e1b\u0e23\u0e30\u0e27\u0e34\u0e07\u0e01\u0e32\u0e23\u0e04\u0e37\u0e19\u0e40\u0e1a\u0e35\u0e49\u0e22\u0e1b\u0e23\u0e30\u0e01\u0e31\u0e19\u0e20\u0e31\u0e22","frequency":2},{"word":"HSBCBWFWORLDTOURFINALS","frequency":2},{"word":"\u0e41\u0e1a\u0e14\u0e21\u0e34\u0e19\u0e15\u0e31\u0e19HSBCBWFWORLDTOURFINALS","frequency":2},{"word":"rapidEyeMovementSleep","frequency":2},{"word":"THAILANDBIGMOVE","frequency":2},{"word":"LaGrandeJatte","frequency":2},{"word":"EnterpriseResourcePlanning","frequency":2},{"word":"\u0e41\u0e2e\u0e23\u0e4c\u0e23\u0e35\u0e48\u0e41\u0e21\u0e47\u0e01\u0e44\u0e01\u0e27","frequency":2},{"word":"\u0e23\u0e2b\u0e31\u0e2a\u0e1e\u0e31\u0e19\u0e18\u0e38\u0e01\u0e23\u0e23\u0e21\u0e02\u0e31\u0e49\u0e19\u0e2a\u0e39\u0e07\u0e2a\u0e38\u0e14","frequency":2},{"word":"Wellforexlimited","frequency":2}]